{
  "type": "Feature",
  "properties": {
    "iso:country":"NL",
    "wof:name":"7707RJ",
    "wof:placetype":"postalcode"
},
  "geometry": {"coordinates":[6.371282,52.611718],"type":"Point"}
}