{
  "type": "Feature",
  "properties": {
    "iso:country":"NL",
    "wof:name":"7735KC",
    "wof:placetype":"postalcode"
},
  "geometry": {"coordinates":[6.454432,52.544334],"type":"Point"}
}