{
  "type": "Feature",
  "properties": {
    "iso:country":"NL",
    "wof:name":"7532RM",
    "wof:placetype":"postalcode"
},
  "geometry": {"coordinates":[6.953232,52.233192],"type":"Point"}
}