{
  "type": "Feature",
  "properties": {
    "iso:country":"NL",
    "wof:name":"4128LP",
    "wof:placetype":"postalcode"
},
  "geometry": {"coordinates":[5.018354,51.952384],"type":"Point"}
}