{
  "type": "Feature",
  "properties": {
    "iso:country":"NL",
    "wof:name":"7597NH",
    "wof:placetype":"postalcode"
},
  "geometry": {"coordinates":[6.802598,52.336897],"type":"Point"}
}