{
  "type": "Feature",
  "properties": {
    "iso:country":"NL",
    "wof:name":"6063NA",
    "wof:placetype":"postalcode"
},
  "geometry": {"coordinates":[6.098738,51.142713],"type":"Point"}
}