{
  "type": "Feature",
  "properties": {
    "iso:country":"NL",
    "wof:name":"2381AM",
    "wof:placetype":"postalcode"
},
  "geometry": {"coordinates":[4.511426,52.116905],"type":"Point"}
}