{
  "type": "Feature",
  "properties": {
    "iso:country":"NL",
    "wof:name":"3931ME",
    "wof:placetype":"postalcode"
},
  "geometry": {"coordinates":[5.432217,52.082369],"type":"Point"}
}