{
  "type": "Feature",
  "properties": {
    "iso:country":"NL",
    "wof:name":"7873TC",
    "wof:placetype":"postalcode"
},
  "geometry": {"coordinates":[6.837365,52.860684],"type":"Point"}
}