{
  "type": "Feature",
  "properties": {
    "iso:country":"NL",
    "wof:name":"4553PA",
    "wof:placetype":"postalcode"
},
  "geometry": {"coordinates":[3.737212,51.284831],"type":"Point"}
}