{
  "type": "Feature",
  "properties": {
    "iso:country":"NL",
    "wof:name":"6012RE",
    "wof:placetype":"postalcode"
},
  "geometry": {"coordinates":[5.77762,51.190063],"type":"Point"}
}