{
  "type": "Feature",
  "properties": {
    "iso:country":"NL",
    "wof:name":"8141RC",
    "wof:placetype":"postalcode"
},
  "geometry": {"coordinates":[6.247158,52.442899],"type":"Point"}
}