{
  "type": "Feature",
  "properties": {
    "iso:country":"NL",
    "wof:name":"6701PB",
    "wof:placetype":"postalcode"
},
  "geometry": {"coordinates":[5.667844,51.957905],"type":"Point"}
}