{
  "type": "Feature",
  "properties": {
    "iso:country":"NL",
    "wof:name":"3899XS",
    "wof:placetype":"postalcode"
},
  "geometry": {"coordinates":[5.512827,52.363889],"type":"Point"}
}