{
  "type": "Feature",
  "properties": {
    "iso:country":"NL",
    "wof:name":"3292LA",
    "wof:placetype":"postalcode"
},
  "geometry": {"coordinates":[4.570376,51.721045],"type":"Point"}
}