{
  "type": "Feature",
  "properties": {
    "iso:country":"NL",
    "wof:name":"8356VZ",
    "wof:placetype":"postalcode"
},
  "geometry": {"coordinates":[5.976319,52.722677],"type":"Point"}
}