{
  "type": "Feature",
  "properties": {
    "iso:country":"NL",
    "wof:name":"7662PB",
    "wof:placetype":"postalcode"
},
  "geometry": {"coordinates":[6.885727,52.437655],"type":"Point"}
}