{
  "type": "Feature",
  "properties": {
    "iso:country":"NL",
    "wof:name":"9974SM",
    "wof:placetype":"postalcode"
},
  "geometry": {"coordinates":[6.293485,53.345411],"type":"Point"}
}