{
  "type": "Feature",
  "properties": {
    "iso:country":"NL",
    "wof:name":"9625PA",
    "wof:placetype":"postalcode"
},
  "geometry": {"coordinates":[6.776016,53.269964],"type":"Point"}
}