{
  "type": "Feature",
  "properties": {
    "iso:country":"NL",
    "wof:name":"4251MS",
    "wof:placetype":"postalcode"
},
  "geometry": {"coordinates":[4.835692,51.77682],"type":"Point"}
}