{
  "type": "Feature",
  "properties": {
    "iso:country":"NL",
    "wof:name":"4515SG",
    "wof:placetype":"postalcode"
},
  "geometry": {"coordinates":[3.625402,51.321781],"type":"Point"}
}