{
  "type": "Feature",
  "properties": {
    "iso:country":"NL",
    "wof:name":"9341TD",
    "wof:placetype":"postalcode"
},
  "geometry": {"coordinates":[6.399789,53.035585],"type":"Point"}
}