{
  "type": "Feature",
  "properties": {
    "iso:country":"NL",
    "wof:name":"2161DZ",
    "wof:placetype":"postalcode"
},
  "geometry": {"coordinates":[4.546628,52.255468],"type":"Point"}
}