{
  "type": "Feature",
  "properties": {
    "iso:country":"NL",
    "wof:name":"3862RW",
    "wof:placetype":"postalcode"
},
  "geometry": {"coordinates":[5.541327,52.203975],"type":"Point"}
}