{
  "type": "Feature",
  "properties": {
    "iso:country":"NL",
    "wof:name":"5691NM",
    "wof:placetype":"postalcode"
},
  "geometry": {"coordinates":[5.467902,51.51909],"type":"Point"}
}