{
  "type": "Feature",
  "properties": {
    "iso:country":"NL",
    "wof:name":"7946LV",
    "wof:placetype":"postalcode"
},
  "geometry": {"coordinates":[6.105127,52.697339],"type":"Point"}
}