{
  "type": "Feature",
  "properties": {
    "iso:country":"NL",
    "wof:name":"3897LN",
    "wof:placetype":"postalcode"
},
  "geometry": {"coordinates":[5.423347,52.372871],"type":"Point"}
}