{
  "type": "Feature",
  "properties": {
    "iso:country":"NL",
    "wof:name":"9623TH",
    "wof:placetype":"postalcode"
},
  "geometry": {"coordinates":[6.693374,53.241631],"type":"Point"}
}