{
  "type": "Feature",
  "properties": {
    "iso:country":"NL",
    "wof:name":"6731SB",
    "wof:placetype":"postalcode"
},
  "geometry": {"coordinates":[5.780505,52.081639],"type":"Point"}
}