{
  "type": "Feature",
  "properties": {
    "iso:country":"NL",
    "wof:name":"3768MX",
    "wof:placetype":"postalcode"
},
  "geometry": {"coordinates":[5.302113,52.151918],"type":"Point"}
}