{
  "type": "Feature",
  "properties": {
    "iso:country":"NL",
    "wof:name":"8101PL",
    "wof:placetype":"postalcode"
},
  "geometry": {"coordinates":[6.240571,52.386519],"type":"Point"}
}