{
  "type": "Feature",
  "properties": {
    "iso:country":"NL",
    "wof:name":"9684TK",
    "wof:placetype":"postalcode"
},
  "geometry": {"coordinates":[7.103883,53.210133],"type":"Point"}
}