{
  "type": "Feature",
  "properties": {
    "iso:country":"NL",
    "wof:name":"7495PH",
    "wof:placetype":"postalcode"
},
  "geometry": {"coordinates":[6.6753,52.262191],"type":"Point"}
}