{
  "type": "Feature",
  "properties": {
    "iso:country":"NL",
    "wof:name":"7261KS",
    "wof:placetype":"postalcode"
},
  "geometry": {"coordinates":[6.462599,52.064604],"type":"Point"}
}