{
  "type": "Feature",
  "properties": {
    "iso:country":"NL",
    "wof:name":"2391NR",
    "wof:placetype":"postalcode"
},
  "geometry": {"coordinates":[4.591255,52.097704],"type":"Point"}
}