{
  "type": "Feature",
  "properties": {
    "iso:country":"NL",
    "wof:name":"4741SN",
    "wof:placetype":"postalcode"
},
  "geometry": {"coordinates":[4.573659,51.594394],"type":"Point"}
}