{
  "type": "Feature",
  "properties": {
    "iso:country":"NL",
    "wof:name":"3911RG",
    "wof:placetype":"postalcode"
},
  "geometry": {"coordinates":[5.568284,51.981738],"type":"Point"}
}