{
  "type": "Feature",
  "properties": {
    "iso:country":"NL",
    "wof:name":"3245LH",
    "wof:placetype":"postalcode"
},
  "geometry": {"coordinates":[4.143252,51.756784],"type":"Point"}
}